dvc_ssh/__init__.py
dvc_ssh/_dvc_ssh_version.py
dvc_ssh/client.py
dvc_ssh/tests/__init__.py
dvc_ssh/tests/cloud.py
dvc_ssh/tests/conftest.py
dvc_ssh/tests/docker-compose.yml
dvc_ssh/tests/fixtures.py
dvc_ssh/tests/test_dvc.py
dvc_ssh/tests/test_fs.py
dvc_ssh/tests/user.key
dvc_ssh/tests/user.key.pub
dvc_ssh-4.2.0.dist-info/LICENSE
dvc_ssh-4.2.0.dist-info/METADATA
dvc_ssh-4.2.0.dist-info/WHEEL
dvc_ssh-4.2.0.dist-info/top_level.txt
dvc_ssh-4.2.0.dist-info/RECORD
