Metadata-Version: 2.2
Name: dvc-ssh
Version: 4.2.0
Summary: ssh plugin for dvc
Author-email: Iterative <support@dvc.org>
Maintainer-email: Iterative <support@dvc.org>
License: Apache License 2.0
Project-URL: Documentation, https://dvc.org/doc
Project-URL: Source, https://github.com/iterative/dvc-ssh
Keywords: dvc,ssh
Classifier: Development Status :: 4 - Beta
Classifier: Programming Language :: Python :: 3
Classifier: Programming Language :: Python :: 3.9
Classifier: Programming Language :: Python :: 3.10
Classifier: Programming Language :: Python :: 3.11
Classifier: Programming Language :: Python :: 3.12
Classifier: Programming Language :: Python :: 3.13
Requires-Python: >=3.9
License-File: LICENSE
Requires-Dist: dvc
Requires-Dist: sshfs[bcrypt]>=2023.4.1
Provides-Extra: dev
Requires-Dist: dvc-ssh[tests]; extra == "dev"
Requires-Dist: mypy==1.14.1; extra == "dev"
Provides-Extra: gssapi
Requires-Dist: sshfs[gssapi]>=2021.11.2; extra == "gssapi"
Provides-Extra: tests
Requires-Dist: dvc[testing]; extra == "tests"
Requires-Dist: pytest<9,>=7; extra == "tests"
Requires-Dist: pytest-cov>=4.1.0; extra == "tests"
Requires-Dist: pytest-xdist>=3.2; extra == "tests"
Requires-Dist: pytest-mock; extra == "tests"
Requires-Dist: pytest-docker<4,>=1; extra == "tests"
